Metadata-Version: 2.1
Name: addlogo
Version: 0.0.3
Summary: Add logo.
Home-page: https://github.com/ternaus/add_logo
Author: Vladimir Iglovikov
Author-email: iglovikov@gmail.com
License: UNKNOWN
Platform: UNKNOWN
Classifier: Programming Language :: Python :: 3
Classifier: License :: OSI Approved :: MIT License
Classifier: Operating System :: OS Independent
License-File: LICENSE
